code_to_prompt/__init__.py
code_to_prompt/cli.py
code_to_prompt/engine.py
code_to_prompt_cli-0.2.3.dist-info/METADATA
code_to_prompt_cli-0.2.3.dist-info/WHEEL
code_to_prompt_cli-0.2.3.dist-info/entry_points.txt
code_to_prompt_cli-0.2.3.dist-info/licenses/LICENSE
code_to_prompt_cli-0.2.3.dist-info/RECORD
