Metadata-Version: 2.4
Name: code-to-prompt-cli
Version: 0.2.3
Summary: CLI tool to convert code folders into a single text file for LLM prompts
Project-URL: Homepage, https://github.com/neha-nambiar/code_to_prompt
Project-URL: Repository, https://github.com/neha-nambiar/code_to_prompt
Author-email: Neha Nambiar <neha.nambiar.1204@gmail.com>
License: MIT
License-File: LICENSE
Keywords: ai,chatgpt,claude,cli,codebase,llm,prompt
Classifier: Development Status :: 4 - Beta
Classifier: Intended Audience :: Developers
Classifier: License :: OSI Approved :: MIT License
Classifier: Operating System :: OS Independent
Classifier: Programming Language :: Python :: 3
Classifier: Programming Language :: Python :: 3.10
Classifier: Programming Language :: Python :: 3.11
Classifier: Programming Language :: Python :: 3.12
Classifier: Topic :: Software Development :: Libraries :: Python Modules
Classifier: Topic :: Utilities
Requires-Python: >=3.10
Requires-Dist: click>=8.0.0
Requires-Dist: rich>=13.0.0
Requires-Dist: tiktoken>=0.5.0
Provides-Extra: dev
Requires-Dist: pytest>=7.0.0; extra == 'dev'
